spgateway_core/__init__.py
spgateway_core/consts.py
spgateway_core/credit_close.py
spgateway_core/mpg.py
spgateway_core/utils.py
spgateway_core-0.1.1.dist-info/LICENSE.txt
spgateway_core-0.1.1.dist-info/METADATA
spgateway_core-0.1.1.dist-info/RECORD
spgateway_core-0.1.1.dist-info/WHEEL
spgateway_core-0.1.1.dist-info/top_level.txt
