Metadata-Version: 2.1
Name: spgateway-core
Version: 0.1.1
Summary: Spgateway core libary
Home-page: https://github.com/cjltsod/django-spgateway
Author: CJLTSOD <github.tsod@tsod.idv.tw>
Author-email: github.tsod@tsod.idv.tw
License: MIT
Keywords: spgateway
Platform: UNKNOWN
Classifier: Development Status :: 2 - Pre-Alpha
Classifier: Programming Language :: Python
Classifier: Programming Language :: Python :: Implementation :: PyPy
Classifier: Programming Language :: Python :: 3.6
Classifier: Topic :: Software Development :: Libraries :: Python Modules
Classifier: Environment :: Web Environment
